trestus/__init__.py
trestus/templates/trestus.css
trestus/templates/trestus.html
trestus-1.0.2.dist-info/DESCRIPTION.rst
trestus-1.0.2.dist-info/METADATA
trestus-1.0.2.dist-info/RECORD
trestus-1.0.2.dist-info/WHEEL
trestus-1.0.2.dist-info/entry_points.txt
trestus-1.0.2.dist-info/metadata.json
trestus-1.0.2.dist-info/top_level.txt
