Metadata-Version: 2.0
Name: trestus
Version: 1.0.2
Summary: Static status page generator that uses a Trello board as a data source
Home-page: http://canonical-ols.github.io/trestus/
Author: Wes Mason
Author-email: wesley.mason@canonical.com
License: AGPL3
Platform: UNKNOWN
Classifier: Topic :: System :: Networking
Classifier: Development Status :: 4 - Beta
Classifier: Programming Language :: Python
Classifier: Intended Audience :: Developers
Classifier: Operating System :: OS Independent
Classifier: Intended Audience :: System Administrators
Classifier: License :: OSI Approved :: GNU Affero General Public License v3 or later (AGPLv3+)
Requires-Dist: jinja2
Requires-Dist: mistune
Requires-Dist: py-trello
Requires-Dist: pyyaml
